beetsplug/yearfixer/__init__.py
beetsplug/yearfixer/about.py
beetsplug/yearfixer/command.py
beetsplug/yearfixer/common.py
beetsplug/yearfixer/config_default.yml
beets_yearfixer-0.0.5.dist-info/LICENSE.txt
beets_yearfixer-0.0.5.dist-info/METADATA
beets_yearfixer-0.0.5.dist-info/WHEEL
beets_yearfixer-0.0.5.dist-info/top_level.txt
beets_yearfixer-0.0.5.dist-info/RECORD
